ananke/Ananke.py
ananke/DensitiesDriver.py
ananke/ErrorModelDriver.py
ananke/ExtinctionDriver.py
ananke/IntegratedLightDriver.py
ananke/Observer.py
ananke/Universe.py
ananke/__init__.py
ananke/__metadata__.py
ananke/_builtin_utils.py
ananke/_constants.py
ananke/_default_error_model.py
ananke/_default_extinction_coeff.py
ananke/_name.py
ananke/_version.py
ananke/utils.py
ananke/__license__/LICENSE
ananke/__license__/__init__.py
ananke-0.4.0.dist-info/licenses/LICENSE
ananke-0.4.0.dist-info/METADATA
ananke-0.4.0.dist-info/WHEEL
ananke-0.4.0.dist-info/top_level.txt
ananke-0.4.0.dist-info/RECORD
