Metadata-Version: 2.4
Name: ananke
Version: 0.4.0
Summary: py-ananke: Provides a pipeline to generate mock synthetic star catalogs from star particle based simulated data.
Home-page: https://github.com/athob/py-ananke
Author: Adrien Thob
Author-email: athob@sas.upenn.edu
Maintainer: Adrien Thob
Maintainer-email: athob@sas.upenn.edu
License: GNU General Public License v3 or later (GPLv3+)
Classifier: Development Status :: 5 - Production/Stable
Classifier: Environment :: Console
Classifier: Intended Audience :: Science/Research
Classifier: License :: OSI Approved :: GNU General Public License v3 or later (GPLv3+)
Classifier: Natural Language :: English
Classifier: Operating System :: Unix
Classifier: Programming Language :: Python :: 3
Classifier: Topic :: Scientific/Engineering :: Astronomy
Requires-Python: >=3.8
License-File: LICENSE
Requires-Dist: numpy<2,>=1.22
Requires-Dist: scipy<2,>=1.7.2
Requires-Dist: pandas<3,>=2
Requires-Dist: docstring_parser<0.17,>=0.16
Requires-Dist: pyvo<2,>=1.6
Requires-Dist: enbid_ananke==0.3.1
Requires-Dist: galaxia_ananke==0.6.1
Dynamic: author
Dynamic: author-email
Dynamic: classifier
Dynamic: description
Dynamic: description-content-type
Dynamic: home-page
Dynamic: license
Dynamic: license-file
Dynamic: maintainer
Dynamic: maintainer-email
Dynamic: requires-dist
Dynamic: requires-python
Dynamic: summary
